club_package1/__init__.py
club_package1/main.py
club_package1/modd1.py
helloasdfsddaniil-0.0.1.dist-info/METADATA
helloasdfsddaniil-0.0.1.dist-info/WHEEL
helloasdfsddaniil-0.0.1.dist-info/top_level.txt
helloasdfsddaniil-0.0.1.dist-info/RECORD
